Workbook

Sheet income statement
A1: A (Particulars) | B1: B (FY2024) | C1: C (FY2023) | D1: D (FY2022)
A2: Net Operating Revenues | B2: 47061 | C2: 45754 | D2: 43004
A3: Cost of Goods Sold | B3: 18324 | C3: 18520 | D3: 18000
A4: Gross Profit | B4: 28737 | C4: 27234 | D4: 25004
A5: Selling, General & Administrative Expenses | B5: 14582 | C5: 13972 | D5: 12880
A6: Other Operating Charges | B6: 4163 | C6: 1951 | D6: 1215
A7: Operating Income | B7: 9992 | C7: 11311 | D7: 10909
A8: Interest Income | B8: 988 | C8: 907 | D8: 449
A9: Interest Expense | B9: 1656 | C9: 1527 | D9: 882
A10: Income Before Taxes | B10: 13086 | C10: 12952 | D10: 11686
A11: Income Taxes | B11: 2437 | C11: 2249 | D11: 2115
A12: Consolidated Net Income | B12: 10649 | C12: 10703 | D12: 9571
A13: Net Income Attributable to Shareowners | B13: 10631 | C13: 10714 | D13: 9542

Sheet balance sheet
A1: Particulars | B1: FY2024 | C1: FY2023
A2: Cash & Cash Equivalents | B2: 10828 | C2: 9366
A3: Short-Term Investments | B3: 2020 | C3: 2997
A4: Accounts Receivable | B4: 3569 | C4: 3410
A5: Inventory | B5: 4728 | C5: 4424
A6: Total Current Assets | B6: 25997 | C6: 26732
A7: Property, Plant & Equipment | B7: 10303 | C7: 9236
A8: Total Assets | B8: 100549 | C8: 97703
A9: Accounts Payable & Accrued Expenses | B9: 21715 | C9: 15485
A10: Short-Term Debt | B10: 1499 | C10: 4557
A11: Current Maturities of Long-Term Debt | B11: 648 | C11: 1960
A12: Long-Term Debt | B12: 42375 | C12: 35547
A13: Total Liabilities | B13: 74177 | C13: 70223
A14: Total Equity | B14: 26372 | C14: 27480

Sheet cash flow
A1: Particulars | B1: FY2024 | C1: FY2023 | D1: FY2022
A2: Consolidated Net Income | B2: 10649 | C2: 10703 | D2: 9571
A3: Depreciation & Amortization | B3: 1075 | C3: 1128 | D3: 1260
A4: Net Cash From Operating Activities (CFO) | B4: 6805 | C4: 11599 | D4: 11018
A5: Purchases of Property, Plant & Equipment (CapEx) | B5: -2064 | C5: -1852 | D5: -1484
A6: Net Cash From Investing Activities | B6: 2524 | C6: -3349 | D6: -763
A7: Net Cash From Financing Activities | B7: -6910 | C7: -8310 | D7: -10250
A8: Ending Cash Balance | B8: 10828 | C8: 9366 | D8: 9519

Sheet ratio analysis
A1: Metric | B1: FY2024 | C1: FY2023 | D1: FY2022 | E1: Formula
A2: Revenue Growth | B2: =('income statement'!C2-'income statement'!B2)/'income statement'!C2 -> -0.028565808 | C2: =('income statement'!C2-'income statement'!D2)/'income statement'!D2 -> 0.06394754 | E2: (Current Revenue − Previous Revenue) / Previous Revenue
A3: Gross Margin | B3: =('income statement'!B2-'income statement'!B3)/'income statement'!B2 -> 0.61063301 | C3: =('income statement'!C2-'income statement'!C3)/'income statement'!C2 -> 0.59522665 | D3: =('income statement'!D2-'income statement'!D3)/'income statement'!D2 -> 0.58143429 | E3: Gross Profit / Revenue
A4: EBITDA | B4: ='income statement'!B7+'cash flow'!B3 -> 11067 | C4: ='income statement'!C7+'cash flow'!C3 -> 12439 | D4: ='income statement'!D7+'cash flow'!D3 -> 12169 | E4: Operating Income + Depreciation & Amortization
A5: EBITDA Margin | B5: =B4/'income statement'!B2 -> 0.23516287 | C5: =C4/'income statement'!C2 -> 0.27186694 | D5: =D4/'income statement'!D2 -> 0.28297368 | E5: EBITDA / Revenue
A6: Operating Margin | B6: ='income statement'!B7/'income statement'!B2 -> 0.21232018 | C6: ='income statement'!C7/'income statement'!C2 -> 0.24721336 | D6: ='income statement'!D7/'income statement'!D2 -> 0.25367408 | E6: Operating Income / Revenue
A7: Net Margin | B7: ='income statement'!B13/'income statement'!B2 -> 0.2258983 | C7: ='income statement'!C13/'income statement'!C2 -> 0.23416532 | D7: ='income statement'!D13/'income statement'!D2 -> 0.22188634 | E7: Net Income / Revenue
A8: DSO | B8: =('balance sheet'!B4/'income statement'!B2)*365 -> 27.680776 | C8: =('balance sheet'!B4/'income statement'!C2)*365 -> 28.4715 | E8: Accounts Receivable / Revenue × 365
A9: DIO | B9: =('balance sheet'!B5/'income statement'!B3)*365 -> 94.178127 | C9: =('balance sheet'!C5/'income statement'!C3)*365 -> 87.190065 | E9: Inventory / Cost of Goods Sold × 365
A10: DPO | B10: =('balance sheet'!B9/'income statement'!B3)*365 -> 432.54611 | C10: =('balance sheet'!C9/'income statement'!C3)*365 -> 305.18494 | E10: Accounts Payable / Cost of Goods Sold × 365
A11: CapEx % Revenue | B11: =ABS('cash flow'!B5)/'income statement'!B2 -> 0.043857972 | C11: =ABS('cash flow'!C5)/'income statement'!C2 -> 0.040477335 | E11: CapEx / Revenue
A12: Debt / EBITDA | B12: =('balance sheet'!B10+'balance sheet'!B12)/'ratio analysis'!B4 -> 3.9643987 | C12: =('balance sheet'!B10+'balance sheet'!B12)/'ratio analysis'!C4 -> 3.5271324 | E12: Total Debt / EBITDA

Sheet Trend Analysis
A1: TREND ANALYSIS
A5: 1. Revenue | F5: 2. Profitability | K5: 3. Working Capital Efficiency | P5: 4. Capital Investment | U5: 5. Leverage
A9: Revenue grew in FY2023 but declined slightly by 2.86% in FY2024, indicating slower sales growth or weaker demand. | F9: Gross margin improved from 58.14% in FY2022 to 61.06% in FY2024, suggesting improved cost management. However, EBITDA and operating margins declined, indicating increased operating expenses. | K9: DSO decreased slightly, reflecting faster customer collections. Inventory days increased, suggesting slower inventory turnover. DPO increased significantly, meaning the company took longer to pay suppliers, which may have improved short-term cash flow. | P9: Capital expenditure remained around 4% of revenue, indicating continued investment in long-term assets while maintaining a relatively stable investment level. | U9: Debt-to-EBITDA increased from 3.53× to 3.96×, indicating that leverage rose relative to operating earnings. This could increase financial risk if earnings continue to decline.
A15: COCA COLA DASHBOARD

Sheet forecast model
A1: Metric | B1: FY2022 | C1: FY2023 | D1: FY2024 | E1: FY2025E | F1: FY2026E | G1: FY2027E
A2: Revenue | B2: 43004 | C2: 45754 | D2: 47061 | E2: =D2*(1+4/100) -> 48943.44 | F2: =E2*(1+4/100) -> 50901.178 | G2: =F2*(1+4/100) -> 52937.225
A3: Revenue Growth | C3: 0.06394754 | D3: -0.028565808 | E3: 0.017690866 | F3: 0.017690866 | G3: 0.017690866
A4: Gross Margin | B4: 0.58143429 | C4: 0.59522665 | D4: 0.61063301 | E4: 0.62603937 | F4: 0.64144573 | G4: 0.65685209
A5: Gross Profit | B5: 25004 | C5: 27234 | D5: 28737 | E5: =E2*D4 -> 29886.48 | F5: =F2*F4 -> 32650.343 | G5: =G2*G4 -> 34771.927
A6: Operating Margin | B6: 0.25367408 | C6: 0.24721336 | D6: 0.21232018 | E6: 0.19638198 | F6: 0.17570503 | G6: 0.15502808
A7: Operating Income | B7: 10909 | C7: 11311 | D7: 9992 | E7: 9820.3333 | F7: 9361.8333 | G7: 8903.3333
A8: Net Margin | B8: 0.22188634 | C8: 0.23416532 | D8: 0.2258983 | E8: 0.23132862 | F8: 0.2333346 | G8: 0.23534058
A9: Net Income | B9: 9542 | C9: 10714 | D9: 10631 | E9: 11384.667 | F9: 11929.167 | G9: 12473.667

Sheet Assumptions
A1: Assumption | B1: 2025E | C1: 2026E | D1: 2027E | E1: 2028E | F1: 2029E
A2: Revenue Growth | B2: 0.04 | C2: 0.04 | D2: 0.035 | E2: 0.03 | F2: 0.03
A3: Gross Margin | B3: 0.6 | C3: 0.6 | D3: 0.6 | E3: 0.6 | F3: 0.6
A4: Operating Margin | B4: 0.24 | C4: 0.24 | D4: 0.24 | E4: 0.24 | F4: 0.24
A5: Tax Rate | B5: 0.19 | C5: 0.19 | D5: 0.19 | E5: 0.19 | F5: 0.19
A6: CapEx % Revenue | B6: 0.04 | C6: 0.04 | D6: 0.04 | E6: 0.04 | F6: 0.04
A7: Depreciation % Revenue | B7: 0.03 | C7: 0.03 | D7: 0.03 | E7: 0.03 | F7: 0.03
A8: SGA% of revenue | B8: 0.205 | C8: 0.205 | D8: 0.205 | E8: 0.205 | F8: 0.205
A10: Note | B10: Balance Sheet prepared using simplified assumptions. Equity roll-forward and detailed financing schedules were not modeled

Sheet Income statement forecasting
A1: Line Item | B1: 2024A | C1: 2025E | D1: 2026E | E1: 2027E | F1: 2028E | G1: 2029E
A2: Revenue | B2: 47061 | C2: =B2*(1+C3) -> 48943.44 | D2: =C2*(1+D3) -> 50656.46 | E2: =D2*(1+E3) -> 52176.154 | F2: =E2*(1+F3) -> 53741.439 | G2: =F2*(1+G3) -> 53741.439
A3: Revenue Growth | B3: =Assumptions!B2 -> 0.04 | C3: =Assumptions!C2 -> 0.04 | D3: =Assumptions!D2 -> 0.035 | E3: =Assumptions!E2 -> 0.03 | F3: =Assumptions!F2 -> 0.03 | G3: =Assumptions!G2 -> 0
A4: Cost of goods sold | B4: 18324 | C4: =C2-C5 -> 19577.376 | D4: =D2-D5 -> 20262.584 | E4: =E2-E5 -> 20870.462 | F4: =F2-F5 -> 21496.576 | G4: =G2-G5 -> 21496.576
A5: Gross Profit | B5: =B2*B6 -> 28236.6 | C5: =C2*C6 -> 29366.064 | D5: =D2*D6 -> 30393.876 | E5: =E2*E6 -> 31305.693 | F5: =F2*F6 -> 32244.863 | G5: =G2*G6 -> 32244.863
A6: Gross Margin | B6: =Assumptions!B3 -> 0.6 | C6: =Assumptions!C3 -> 0.6 | D6: =Assumptions!D3 -> 0.6 | E6: =Assumptions!E3 -> 0.6 | F6: =Assumptions!F3 -> 0.6 | G6: =60% -> 0.6
A7: SG&A Expense | B7: =B2*B8 -> 9647.505 | C7: =C2*C8 -> 10033.405 | D7: =D2*D8 -> 10384.574 | E7: =E2*E8 -> 10696.112 | F7: =F2*F8 -> 11016.995 | G7: =G2*G8 -> 11016.995
A8: SG&A % of Revenue | B8: 0.205 | C8: 0.205 | D8: 0.205 | E8: 0.205 | F8: 0.205 | G8: 0.205
A9: Depreciation & Amortization | B9: =B2*B10 -> 1411.83 | C9: =C2*C10 -> 1468.3032 | D9: =D2*D10 -> 1519.6938 | E9: =E2*E10 -> 1565.2846 | F9: =F2*F10 -> 1612.2432 | G9: =G2*G10 -> 1612.2432
A10: D&A % of Revenue | B10: 0.03 | C10: 0.03 | D10: 0.03 | E10: 0.03 | F10: 0.03 | G10: 0.03
A11: Operating Income (EBIT) | B11: =B2*B12 -> 11294.64 | C11: =C2*C12 -> 11746.426 | D11: =D2*D12 -> 12157.55 | E11: =E2*E12 -> 12522.277 | F11: =F2*F12 -> 12897.945 | G11: =G2*G12 -> 12897.945
A12: Operating Margin | B12: 0.24 | C12: 0.24 | D12: 0.24 | E12: 0.24 | F12: 0.24 | G12: 0.24
A13: Interest Expense | B13: 1656 | C13: 1656 | D13: 1656 | E13: 1656 | F13: 1656 | G13: 1656
A14: Earnings Before Tax (EBT) | B14: =B11-B13 -> 9638.64 | C14: =C11-C13 -> 10090.426 | D14: =D11-D13 -> 10501.55 | E14: =E11-E13 -> 10866.277 | F14: =F11-F13 -> 11241.945 | G14: =G11-G13 -> 11241.945
A15: Tax Rate | B15: 0.19 | C15: 0.19 | D15: 0.19 | E15: 0.19 | F15: 0.19 | G15: 0.19
A16: Tax Expense | B16: =B14*19/100 -> 1831.3416 | C16: =C14*19/100 -> 1917.1809 | D16: =D14*19/100 -> 1995.2946 | E16: =E14*19/100 -> 2064.5926 | F16: =F14*19/100 -> 2135.9696 | G16: =G14*19/100 -> 2135.9696
A17: Net Income | B17: =B14-B16 -> 7807.2984 | C17: =C14-C16 -> 8173.2447 | D17: =D14-D16 -> 8506.2559 | E17: =E14-E16 -> 8801.6844 | F17: =F14-F16 -> 9105.9757 | G17: =G14-G16 -> 9105.9757
A18: Net Margin | B18: =B17/B2 -> 0.16589742 | C18: =C17/C2 -> 0.16699367 | D18: =D17/D2 -> 0.16792046 | E18: =E17/E2 -> 0.1686917 | F18: =F17/F2 -> 0.16944049 | G18: =G17/G2 -> 0.16944049

Sheet Balance sheet forecasting
A1: Particulars | B1: FY2024 | C1: FY2025E | D1: FY2026E | E1: FY2027E | F1: FY2028E | G1: FY2029E | H1: Forecast Method
A2: Cash & Cash Equivalents | B2: 10828 | C2: ='Cash flow forcasting'!C18 -> 15001.108 | D2: ='Cash flow forcasting'!D18 -> 20311.992 | E2: ='Cash flow forcasting'!E18 -> 25545.84 | F2: ='Cash flow forcasting'!F18 -> 30868.607 | G2: ='Cash flow forcasting'!G18 -> 36189.263 | H2: Plug
A3: Short-Term Investments | B3: 2020 | C3: 2020 | D3: 2020 | E3: 2020 | F3: 2020 | G3: 2020 | H3: Constant
A4: Accounts Receivable | B4: 3569 | C4: 3711.76 | D4: 3529.35 | E4: 3603.37 | F4: 3603.37 | G4: 3603.37 | H4: % of Revenue
A5: Inventory | B5: 4728 | C5: 5051.4 | D5: 4578.84 | E5: 4786.08 | F5: 4805.44 | G5: 4723.45 | H5: % of COGS
A6: other current asset | B6: 4852 | C6: 4852 | D6: 4852 | E6: 4852 | F6: 4852 | G6: 4852
A7: Total Current Assets | B7: =SUM(B2:B6) -> 25997 | C7: =SUM(C2:C6) -> 30636.268 | D7: =SUM(D2:D6) -> 35292.182 | E7: =SUM(E2:E6) -> 40807.29 | F7: =SUM(F2:F6) -> 46149.417 | G7: =SUM(G2:G6) -> 51388.083 | H7: Formula
A8: Property, Plant & Equipment | B8: 10303 | C8: 10715 | D8: 11144 | E8: 11590 | F8: 12054 | G8: 12536 | H8: 4% Growth
A9: Other Assets | B9: 64249 | C9: 64249 | D9: 64249 | E9: 64249 | F9: 64249 | G9: 64249 | H9: Formula
A10: Total Assets | B10: =B7+B8+B9 -> 100549 | C10: =C7+C8+C9 -> 105600.27 | D10: =D7+D8+D9 -> 110685.18 | E10: =E7+E8+E9 -> 116646.29 | F10: =F7+F8+F9 -> 122452.42 | G10: =G7+G8+G9 -> 128173.08
A11: Accounts Payable & Accrued Expenses | B11: 21715 | C11: 22584 | D11: 23487 | E11: 24426 | F11: 25403 | G11: 26419 | H11: 4% Growth
A12: Short-Term Debt | B12: 1499 | C12: 1499 | D12: 1499 | E12: 1499 | F12: 1499 | G12: 1499 | H12: Constant
A13: Current Maturities of Long-Term Debt | B13: 648 | C13: 648 | D13: 648 | E13: 648 | F13: 648 | G13: 648 | H13: Constant
A14: Other liabilities | B14: 7940 | C14: 7940 | D14: 7940 | E14: 7940 | F14: 7940 | G14: 7940
A15: Long-Term Debt | B15: 42375 | C15: 42375 | D15: 42375 | E15: 42375 | F15: 42375 | G15: 42375 | H15: Constant
A16: Total Liabilities | B16: =SUM(B11:B15) -> 74177 | C16: =SUM(C11:C15) -> 75046 | D16: =SUM(D11:D15) -> 75949 | E16: =SUM(E11:E15) -> 76888 | F16: =SUM(F11:F15) -> 77865 | G16: =SUM(G11:G15) -> 78881 | H16: Formula
A17: Total Equity | B17: 26372 | C17: 26372 | D17: 26372 | E17: 26372 | F17: 26372 | G17: 26372
A19: Balance check | B19: =B10-B16-B17 -> 0 | C19: =C10-C16-C17 -> 4182.268 | D19: =D10-D16-D17 -> 8364.1824 | E19: =E10-E16-E17 -> 13386.29 | F19: =F10-F16-F17 -> 18215.417 | G19: =G10-G16-G17 -> 22920.083

Sheet Cash flow forcasting
A1: Cash Flow Statement | B1: 2024A | C1: 2025E | D1: 2026E | E1: 2027E | F1: 2028E | G1: 2029E | H1: Forecast Method
A2: Operating Activities
A3: Net Income | B3: ='Income statement forecasting'!B17 -> 7807.2984 | C3: ='Income statement forecasting'!C17 -> 8173.2447 | D3: ='Income statement forecasting'!D17 -> 8506.2559 | E3: ='Income statement forecasting'!E17 -> 8801.6844 | F3: ='Income statement forecasting'!F17 -> 9105.9757 | G3: ='Income statement forecasting'!G17 -> 9105.9757 | H3: Link from Income Statement
A4: Depreciation & Amortization | B4: ='Income statement forecasting'!B9 -> 1411.83 | C4: ='Income statement forecasting'!C9 -> 1468.3032 | D4: ='Income statement forecasting'!D9 -> 1519.6938 | E4: ='Income statement forecasting'!E9 -> 1565.2846 | F4: ='Income statement forecasting'!F9 -> 1612.2432 | G4: ='Income statement forecasting'!G9 -> 1612.2432 | H4: Link from Income Statement
A5: Change in Accounts Receivable | B5: ='Balance sheet forecasting'!C4-'Balance sheet forecasting'!B4 -> 142.76 | C5: ='Balance sheet forecasting'!D4-'Balance sheet forecasting'!C4 -> -182.41 | D5: ='Balance sheet forecasting'!E4-'Balance sheet forecasting'!D4 -> 74.02 | E5: ='Balance sheet forecasting'!F4-'Balance sheet forecasting'!E4 -> 0 | F5: ='Balance sheet forecasting'!G4-'Balance sheet forecasting'!F4 -> 0 | G5: 0 | H5: Balance Sheet
A6: Change in Inventory | B6: ='Balance sheet forecasting'!C5-'Balance sheet forecasting'!B5 -> 323.4 | C6: ='Balance sheet forecasting'!D5-'Balance sheet forecasting'!C5 -> -472.56 | D6: ='Balance sheet forecasting'!E5-'Balance sheet forecasting'!D5 -> 207.24 | E6: ='Balance sheet forecasting'!F5-'Balance sheet forecasting'!E5 -> 19.36 | F6: ='Balance sheet forecasting'!G5-'Balance sheet forecasting'!F5 -> -81.99 | G6: -9.1 | H6: Balance Sheet
A7: Change in Accounts Payable | B7: ='Balance sheet forecasting'!C11-'Balance sheet forecasting'!B11 -> 869 | C7: ='Balance sheet forecasting'!D11-'Balance sheet forecasting'!C11 -> 903 | D7: ='Balance sheet forecasting'!E11-'Balance sheet forecasting'!D11 -> 939 | E7: ='Balance sheet forecasting'!F11-'Balance sheet forecasting'!E11 -> 977 | F7: ='Balance sheet forecasting'!G11-'Balance sheet forecasting'!F11 -> 1016 | G7: 941 | H7: Balance Sheet
A8: Net Cash from Operating Activities | B8: =SUM(B3:B7) -> 10554.288 | C8: =SUM(C3:C7) -> 9889.5779 | D8: =SUM(D3:D7) -> 11246.21 | E8: =SUM(E3:E7) -> 11363.329 | F8: =SUM(F3:F7) -> 11652.229 | G8: =SUM(G3:G7) -> 11650.119 | H8: Formula
A9: Investing Activities
A10: Capital Expenditures (CapEx) | B10: =-'Income statement forecasting'!B2*5% -> -2353.05 | C10: =-'Income statement forecasting'!C2*5% -> -2447.172 | D10: =-'Income statement forecasting'!D2*5% -> -2532.823 | E10: =-'Income statement forecasting'!E2*5% -> -2608.8077 | F10: =-'Income statement forecasting'!F2*5% -> -2687.0719 | G10: =-'Income statement forecasting'!G2*5% -> -2687.0719 | H10: Assumption
A11: Net Cash from Investing Activities | B11: =B10 -> -2353.05 | C11: =C10 -> -2447.172 | D11: =D10 -> -2532.823 | E11: =E10 -> -2608.8077 | F11: =F10 -> -2687.0719 | G11: =G10 -> -2687.0719 | H11: Formula
A12: Financing Activities
A13: Debt Issued / (Repaid) | B13: 0 | C13: 0 | D13: 0 | E13: 0 | F13: 0 | G13: 0 | H13: Constant
A14: Dividends Paid | B14: =-'Income statement forecasting'!B17*40% -> -3122.9194 | C14: =-'Income statement forecasting'!C17*40% -> -3269.2979 | D14: =-'Income statement forecasting'!D17*40% -> -3402.5024 | E14: =-'Income statement forecasting'!E17*40% -> -3520.6738 | F14: =-'Income statement forecasting'!F17*40% -> -3642.3903 | G14: =-'Income statement forecasting'!G17*40% -> -3642.3903 | H14: Assumption
A15: Net Cash from Financing Activities | B15: =B14 -> -3122.9194 | C15: =C14 -> -3269.2979 | D15: =D14 -> -3402.5024 | E15: =E14 -> -3520.6738 | F15: =F14 -> -3642.3903 | G15: =G14 -> -3642.3903 | H15: Formula
A16: Net Increase / (Decrease) in Cash | B16: =B8+B11+B15 -> 5078.319 | C16: =C8+C11+C15 -> 4173.108 | D16: =D8+D11+D15 -> 5310.8843 | E16: =E8+E11+E15 -> 5233.8475 | F16: =F8+F11+F15 -> 5322.7666 | G16: =G8+G11+G15 -> 5320.6566 | H16: Formula
A17: Beginning Cash | B17: 9366 | C17: 10828 | D17: =C18 -> 15001.108 | E17: =D18 -> 20311.992 | F17: =E18 -> 25545.84 | G17: =F18 -> 30868.607 | H17: Link
A18: Ending Cash | B18: =B17+B16 -> 14444.319 | C18: =C17+C16 -> 15001.108 | D18: =D17+D16 -> 20311.992 | E18: =E17+E16 -> 25545.84 | F18: =F17+F16 -> 30868.607 | G18: =G17+G16 -> 36189.263 | H18: Link to Balance Sheet

Sheet Dcf Valuation
A1: Particulars | B1: 2025E | C1: 2026E | D1: 2027E | E1: 2028E | F1: 2029E
A2: EBIT | B2: ='Income statement forecasting'!C11 -> 11746.426 | C2: ='Income statement forecasting'!D11 -> 12157.55 | D2: ='Income statement forecasting'!E11 -> 12522.277 | E2: ='Income statement forecasting'!F11 -> 12897.945 | F2: ='Income statement forecasting'!G11 -> 12897.945
A3: Less: Taxes | B3: ='Income statement forecasting'!B16 -> 1831.3416 | C3: ='Income statement forecasting'!C16 -> 1917.1809 | D3: ='Income statement forecasting'!D16 -> 1995.2946 | E3: ='Income statement forecasting'!E16 -> 2064.5926 | F3: ='Income statement forecasting'!F16 -> 2135.9696
A4: NOPAT | B4: =B2*(1-'Income statement forecasting'!B15) -> 9514.6047 | C4: =C2*(1-'Income statement forecasting'!C15) -> 9847.6159 | D4: =D2*(1-'Income statement forecasting'!D15) -> 10143.044 | E4: =E2*(1-'Income statement forecasting'!E15) -> 10447.336 | F4: =F2*(1-'Income statement forecasting'!F15) -> 10447.336 | I4: Historical Financial Statements │ ▼ Forecast Revenue, Expenses, EBIT, CapEx, Working Capital │ ▼ Calculate Free Cash Flow (FCFF) │ ▼ Calculate Terminal Value │ ▼ Discount FCFF & Terminal Value using WACC │ ▼ Enterprise Value │ ▼ Less Debt + Add Cash │ ▼ Equity Value │ ▼ Implied Share Price
A5: + Depreciation & Amortization | B5: ='Income statement forecasting'!C9 -> 1468.3032 | C5: ='Income statement forecasting'!D9 -> 1519.6938 | D5: ='Income statement forecasting'!E9 -> 1565.2846 | E5: ='Income statement forecasting'!F9 -> 1612.2432 | F5: ='Income statement forecasting'!G9 -> 1612.2432
A6: − Capital Expenditures | B6: ='Cash flow forcasting'!C10 -> -2447.172 | C6: ='Cash flow forcasting'!D10 -> -2532.823 | D6: ='Cash flow forcasting'!E10 -> -2608.8077 | E6: ='Cash flow forcasting'!F10 -> -2687.0719 | F6: ='Cash flow forcasting'!G10 -> -2687.0719
A7: − Change in Net Working Capital | B7: 3770 | C7: 3753 | D7: 4576 | E7: 4365 | F7: 4223
A8: Free Cash Flow to Firm (FCFF) | B8: =B2-B3+B5+B6-B7 -> 5166.2152 | C8: =C2-C3+C5+C6-C7 -> 5474.2404 | D8: =D2-D3+D5+D6-D7 -> 4907.4593 | E8: =E2-E3+E5+E6-E7 -> 5393.5239 | F8: =F2-F3+F5+F6-F7 -> 5464.1469
A9: (Weighted average cost of capital) To convert future cash flow to current rate | B9: 0.08 | C9: 0.08 | D9: 0.08 | E9: 0.08 | F9: 0.08 | G9: Asssumption
A10: Discount Rate | B10: =1/(1+8%)^1 -> 0.92592593 | C10: =1/(1+8%)^2 -> 0.85733882 | D10: =1/(1+8%)^3 -> 0.79383224 | E10: =1/(1+8%)^4 -> 0.73502985 | F10: =1/(1+8%)^5 -> 0.6805832
A11: PV(present value) of FCFF | B11: =B8*B10 -> 4783.5326 | C11: =C8*C10 -> 4693.2788 | D11: =D8*D10 -> 3895.6994 | E11: =E8*E10 -> 3964.4011 | F11: =F8*F10 -> 3718.8066
A12: Terminal growth rate | B12: 0.025 | C12: 0.025 | D12: 0.025 | E12: 0.025 | F12: 0.025 | G12: Assumption
A13: Terminal value (represents all future cash flows beyond your forecast years.) | B13: =F8*(1+B12)/(8%-2.5%) -> 101831.83 | G13: =F8*(1+0.02)/(0.07-0.02) -> 111468.6
A14: PV(TV) | B14: =B13/(1+B9)^5 -> 69305.032 | G14: =G13/(1+0.07)^5 -> 79475.569
A15: EV(Enterprise value) | B15: =SUM(B11:F11)+B14 -> 90360.75 | G15: =SUM(B11:F11)+G14 -> 100531.29
A16: Equity Value | B16: =B15-('Balance sheet forecasting'!B15+'Balance sheet forecasting'!B12)+'Balance sheet forecasting'!B2 -> 57314.75 | G16: =G15-('Balance sheet forecasting'!B12+'Balance sheet forecasting'!B15)+'Balance sheet forecasting'!B2 -> 67485.288
A17: Target Price | B17: =B16/E19 -> 13.298086 | G17: =G16/'ratio analysis'!B8 -> 2437.984
D19: DSO(Daily shares outstanding) | E19: =4310 -> 4310

Sheet DCF Summary
A1: DCF Valuation
A4: DCF estimates intrinsic value based on future FCFF. If target price > current market price → potentially undervalued. If target price < current market price → potentially overvalued.
A13: ='Dcf Valuation'!B17 -> 13.298086 | B13: 0.07 | C13: 0.08 | D13: 0.09
A14: 0.02 | B14: ='Dcf Valuation'!G17 -> 2437.984 | C14: 1850.7 | D14: 1436.3
A15: 0.025 | B15: 2772.6 | C15: 2070.6 | D15: 1590
A16: 0.03 | B16: 3191 | C16: 2334.4 | D16: 1769.2
A17: Senstivity Analysis

Sheet Trading Comps
A1: Company | B1: Share Price | C1: Shares Outstanding | D1: Market Cap | E1: Total Debt | F1: Cash | G1: Enterprise Value | H1: Revenue (LTM) | I1: EBITDA (LTM) | J1: EV/Revenue | K1: EV/EBITDA
A2: PepsiCo | B2: 109.08 | C2: 1.37 | D2: 189.02 | E2: 37.224 | F2: 9.53 | G2: 216.714 | H2: 93.925 | I2: 15.676 | J2: 2.307 | K2: 13.824
A3: Coca-Cola | B3: 72 | C3: 4.31 | D3: 310.32 | E3: 3.375 | F3: 1.61 | G3: 312.085 | H3: 13.416 | I3: 2.495 | J3: 23.264 | K3: 125.084
A4: Monster Beverage | B4: 63 | C4: 0.97 | D4: 61.11 | E4: 0.37 | F4: 1.68 | G4: 59.8 | H4: 7.49 | I4: 2.31 | J4: 7.984 | K4: 25.887
A5: Keurig Dr Pepper (KDP) | B5: 31.7 | C5: 1.36 | D5: 43.11 | E5: 16.8 | F5: 0.49 | G5: 59.42 | H5: 15.35 | I5: 4.15 | J5: 3.871 | K5: 14.318
A6: National Beverage | B6: 44 | C6: 0.094 | D6: 4.14 | E6: 0.06 | F6: 0.35 | G6: 3.85 | H6: 1.19 | I6: 0.23 | J6: 3.235 | K6: 16.739
A7: average | B7: =AVERAGE(B2:B6) -> 63.956 | C7: =AVERAGE(C2:C6) -> 1.6208 | D7: =AVERAGE(D2:D6) -> 121.54 | E7: =AVERAGE(E2:E6) -> 11.5658 | F7: =AVERAGE(F2:F6) -> 2.732 | G7: =AVERAGE(G2:G6) -> 130.3738 | H7: =AVERAGE(H2:H6) -> 26.2742 | I7: =AVERAGE(I2:I6) -> 4.9722 | ... K7: =AVERAGE(K2:K6) -> 39.1704
A8: median | B8: =MEDIAN(B2:B7) -> 63.478 | C8: =MEDIAN(C2:C7) -> 1.365 | D8: =MEDIAN(D2:D7) -> 91.325 | E8: =MEDIAN(E2:E7) -> 7.4704 | F8: =MEDIAN(F2:F7) -> 1.645 | G8: =MEDIAN(G2:G7) -> 95.0869 | H8: =MEDIAN(H2:H7) -> 14.383 | I8: =MEDIAN(I2:I7) -> 3.3225 | ... K8: =MEDIAN(K2:K7) -> 21.313
D10: Find Similar Public Companies │ ▼ Collect Market Data (Share Price, Market Cap, Debt, Cash, EBITDA, Revenue) │ ▼ Calculate Trading Multiples (EV/Revenue, EV/EBITDA) │ ▼ Find Mean & Median Multiples │ ▼ Apply Multiples to OUR Target Company │ ▼ Estimate Enterprise Value │ ▼ Less Debt + Add Cash │ ▼ Equity Value │ ▼ Implied Share Price

Sheet Transaction Analysis
A1: Acquirer | B1: Target | C1: EV ($M) | D1: Revenue ($M) | E1: EBITDA ($M) | F1: EV/Revenue | G1: EV/EBITDA
A2: BigTech | B2: AppCo | C2: 2500 | D2: 500 | E2: 100 | F2: =C2/D2 -> 5 | G2: =C2/E2 -> 25
A3: CloudCorp | B3: SaaSTech | C3: 1800 | D3: 400 | E3: 150 | F3: =C3/D3 -> 4.5 | G3: =C3/E3 -> 12
A4: PE Fund A | B4: DataPlatform | C4: 1200 | D4: 280 | E4: 110 | F4: =C4/D4 -> 4.2857143 | G4: =C4/E4 -> 10.909091
A5: StrategicCo | B5: SoftModule | C5: 3000 | D5: 600 | E5: 200 | F5: =C5/D5 -> 5 | G5: =C5/E5 -> 15
A6: TechGiant | B6: AnalyticsPro | C6: 2200 | D6: 440 | E6: 180 | F6: =C6/D6 -> 5 | G6: =C6/E6 -> 12.222222
A8: Statistic | B8: EV/Revenue | C8: EV/EBITDA
A9: Mean | B9: =AVERAGE(F2:F6) -> 4.7571429 | C9: =AVERAGE(G2:G6) -> 15.026263
A10: Median | B10: =MEDIAN(F2:F6) -> 5 | C10: =MEDIAN(G2:G6) -> 12.222222 | G10: Past Acquisitions │ ▼ Company A bought Company B Company C bought Company D Company E bought Company F │ ▼ Calculate transaction multiples (EV/Revenue, EV/EBITDA) │ ▼ Find the median multiple │ ▼ Apply it to OUR target company │ ▼ Estimate acquisition value
A11: High | B11: =MAX(F2:F6) -> 5 | C11: =MAX(G2:G6) -> 25
A12: Low | B12: =MIN(F2:F6) -> 4.2857143 | C12: =MIN(G2:G6) -> 10.909091
A14: TARGET COMPANY(MidTech Corp) | D14: Given
A18: Metric | B18: Value
A19: Revenue | B19: 900
A20: EBITDA | B20: 180
A21: Debt | B21: 150
A22: Cash | B22: 100
A23: Shares Outstanding | B23: 80
A24: Current Share Price | B24: 22
A26: Valuation Method | B26: Formula | C26: Enterprise Value
A27: EV/Revenue | B27: Revenue × Median EV/Revenue | C27: =B19*B10 -> 4500
A28: EV/EBITDA | B28: EBITDA × Median EV/EBITDA | C28: =B20*C10 -> 2200
A30: EV to EV
A32: Valuation Method | B32: Enterprise Value | C32: Less: Debt | D32: Add: Cash | E32: Equity Value
A33: EV/Revenue | B33: 4500 | C33: 150 | D33: 100 | E33: =B33-C33+D33 -> 4450
A34: EV/EBITDA | B34: 2200 | C34: 150 | D34: 100 | E34: =B34-C34+D34 -> 2150
A36: Implied Share Price
A38: Valuation Method | B38: Equity Value | C38: Shares Outstanding | D38: Implied Share Price
A39: EV/Revenue | B39: 4450 | C39: 80 | D39: =B39/C39 -> 55.625
A40: EV/EBITDA | B40: 2150 | C40: 80 | D40: =B40/C40 -> 26.875

Sheet LBO Assumptions
A1: Particulars | B1: Value | O1: SPONSOR RETURNS SECTION
A2: LTM EBITDA | B2: 80 | F2: OPERATING FORECAST
A3: Entry Multiple | B3: 7.5
A4: Entry Enterprise Value | B4: =B2*B3 -> 600 | F4: Particulars | G4: Year 0 | H4: Year 1 | I4: Year 2 | J4: Year 3 | K4: Year 4 | L4: Year 5 | O4: Particulars | P4: Value
A5: Existing Debt | B5: 250 | F5: Revenue | G5: =B2/B12 -> 444.44444 | H5: =G5*(1+G6) -> 471.11111 | I5: =H5*(1+H6) -> 499.37778 | J5: =I5*(1+I6) -> 529.34044 | K5: =J5*(1+J6) -> 561.10087 | L5: =K5*(1+K6) -> 594.76692 | O5: Exit EBITDA | P5: =L8 -> 130.84872
A6: Cash | B6: 400 | F6: Growth % | G6: 0.06 | H6: 0.06 | I6: 0.06 | J6: 0.06 | K6: 0.06 | L6: 0.06 | O6: Exit Multiple | P6: 8
A7: Equity Purchase Price | B7: =B4-B5+B6 -> 750 | F7: EBITDA Margin | G7: 0.18 | H7: =18%+0.8% -> 0.188 | I7: =H7+0.8% -> 0.196 | J7: =I7+0.8% -> 0.204 | K7: =J7+0.8% -> 0.212 | L7: =K7+0.8% -> 0.22 | O7: Exit Enterprise Value | P7: =P5*P6 -> 1046.7898
A8: Holding Period | B8: 5 Years | F8: EBITDA | G8: =G5*G7 -> 80 | H8: =H5*H7 -> 88.568889 | I8: =I5*I7 -> 97.878044 | J8: =J5*J7 -> 107.98545 | K8: =K5*K7 -> 118.95338 | L8: =L5*L7 -> 130.84872 | O8: Less: Ending Debt | P8: =L26 -> 28.944523
A9: Exit Multiple | B9: 8.0x | F9: D&A | G9: =$B15*G5 -> 17.777778 | H9: =$B15*H5 -> 18.844444 | I9: =$B15*I5 -> 19.975111 | J9: =$B15*J5 -> 21.173618 | K9: =$B15*K5 -> 22.444035 | L9: =$B15*L5 -> 23.790677 | O9: Add: Cash | P9: 0
A10: Tax Rate | B10: 0.25 | F10: EBIT | G10: =G8-G9 -> 62.222222 | H10: =H8-H9 -> 69.724444 | I10: =I8-I9 -> 77.902933 | J10: =J8-J9 -> 86.811833 | K10: =K8-K9 -> 96.50935 | L10: =L8-L9 -> 107.05805 | O10: Exit Equity Value | P10: =P7-P8+P9 -> 1017.8453
A11: Revenue Growth | B11: 0.06 | F11: Taxes | G11: =$B10*G10 -> 15.555556 | H11: =$B10*H10 -> 17.431111 | I11: =$B10*I10 -> 19.475733 | J11: =$B10*J10 -> 21.702958 | K11: =$B10*K10 -> 24.127337 | L11: =$B10*L10 -> 26.764512 | O11: Initial Equity Investment | P11: =B21 -> 750
A12: Starting EBITDA Margin | B12: 0.18 | F12: NOPAT | G12: =G10-G11 -> 46.666667 | H12: =H10-H11 -> 52.293333 | I12: =I10-I11 -> 58.4272 | J12: =J10-J11 -> 65.108875 | K12: =K10-K11 -> 72.382012 | L12: =L10-L11 -> 80.293535 | O12: Money Multiple (MoM) | P12: =P10/P11 -> 1.357127
A13: Ending EBITDA Margin | B13: 0.22 | F13: CapEx | G13: =G5*$B14 -> 13.333333 | H13: =H5*$B14 -> 14.133333 | I13: =I5*$B14 -> 14.981333 | J13: =J5*$B14 -> 15.880213 | K13: =K5*$B14 -> 16.833026 | L13: =L5*$B14 -> 17.843008 | O13: IRR | P13: =IRR(P20:P25) -> 0.21717033
A14: CapEx % Revenue | B14: 0.03 | F14: Change in Working Capital | G14: 0 | H14: =(H5-G5)*$B16 -> 0.53333333 | I14: =(I5-H5)*$B16 -> 0.56533333 | J14: =(J5-I5)*$B16 -> 0.59925333 | K14: =(K5-J5)*$B16 -> 0.63520853 | L14: =(L5-K5)*$B16 -> 0.67332105
A15: D&A % Revenue | B15: 0.04 | F15: Free Cash Flow | G15: =G12+G9-G13-G14 -> 51.111111 | H15: =H12+H9-H13-H14 -> 56.471111 | I15: =I12+I9-I13-I14 -> 62.855644 | J15: =J12+J9-J13-J14 -> 69.803026 | K15: =K12+K9-K13-K14 -> 77.357813 | L15: =L12+L9-L13-L14 -> 85.567883
A16: Working Capital % Revenue Growth | B16: 0.02
A18: Source and Uses | F18: DEBT SCHEDULE
O19: Year | P19: Cash Flow
A20: Uses | B20: Value | F20: Debt Schedule | G20: Year 0 | H20: Year 1 | I20: Year 2 | J20: Year 3 | K20: Year 4 | L20: Year 5 | O20: 0 | P20: -381
A21: Equity Purchase Price | B21: 750 | F21: Beginning Debt | G21: 381 | H21: 381 | I21: =H26 -> 324.52889 | J21: =I26 -> 261.67324 | K21: =J26 -> 191.87022 | L21: =K26 -> 114.51241 | O21: 1 | P21: 0
A22: Transaction Fees | B22: 12 | F22: Interest Rate | G22: 0.08 | H22: 0.08 | I22: 0.08 | J22: 0.08 | K22: 0.08 | L22: 0.08 | O22: 2 | P22: 0
A23: Total Uses | B23: 762 | F23: Interest Expense | H23: =H21*H22 -> 30.48 | I23: =I21*I22 -> 25.962311 | J23: =J21*J22 -> 20.93386 | K23: =K21*K22 -> 15.349617 | L23: =L21*L22 -> 9.1609925 | O23: 3 | P23: 0
F24: Free Cash Flow | H24: =H15 -> 56.471111 | I24: =I15 -> 62.855644 | J24: =J15 -> 69.803026 | K24: =K15 -> 77.357813 | L24: =L15 -> 85.567883 | O24: 4 | P24: 0
F25: Debt Repayment | H25: =MIN(H21,H24) -> 56.471111 | I25: =MIN(I21,I24) -> 62.855644 | J25: =MIN(J21,J24) -> 69.803026 | K25: =MIN(K21,K24) -> 77.357813 | L25: =MIN(L21,L24) -> 85.567883 | O25: 5 | P25: =P10 -> 1017.8453
A26: Sources | B26: Value | F26: Ending Debt | G26: 381 | H26: =H21-H25 -> 324.52889 | I26: =I21-I25 -> 261.67324 | J26: =J21-J25 -> 191.87022 | K26: =K21-K25 -> 114.51241 | L26: =L21-L25 -> 28.944523
A27: New Debt | B27: 381
A28: Sponsor Equity | B28: 381
A29: Total Sources | B29: 762
